bolb/__init__.py
bolb-1.0.0.dist-info/LICENSE
bolb-1.0.0.dist-info/WHEEL
bolb-1.0.0.dist-info/METADATA
bolb-1.0.0.dist-info/RECORD
