Metadata-Version: 2.1
Name: bolb
Version: 1.0.0
Summary: bolb
Home-page: https://github.com/vcokltfre/bolb
License: MIT
Keywords: bolb
Author: vcokltfre
Author-email: vcokltfre@gmail.com
Requires-Python: >=3.10,<4.0
Classifier: License :: OSI Approved :: MIT License
Classifier: Programming Language :: Python :: 3
Classifier: Programming Language :: Python :: 3.10
Requires-Dist: taskipy (>=1.9.0,<2.0.0)
Project-URL: Repository, https://github.com/vcokltfre/bolb
